LICENSE
README.md
setup.cfg
setup.py
pytorch_model_trainer.egg-info/PKG-INFO
pytorch_model_trainer.egg-info/SOURCES.txt
pytorch_model_trainer.egg-info/dependency_links.txt
pytorch_model_trainer.egg-info/top_level.txt
pytorch_trainer/__init__.py
pytorch_trainer/trainer.py
pytorch_trainer/callbacks/__init__.py
pytorch_trainer/callbacks/base_callback.py
pytorch_trainer/callbacks/callback_dispatcher.py
pytorch_trainer/callbacks/callbacks.py
pytorch_trainer/metrics/__init__.py
pytorch_trainer/metrics/accuracy_metrics.py
pytorch_trainer/metrics/base_metric.py
pytorch_trainer/metrics/classification_metrics.py
pytorch_trainer/metrics/metric_dispatcher.py