Metadata-Version: 2.1
Name: pytorch-model-trainer
Version: 0.1.3
Summary: A tool to train pytorch models implementing an interface similar to keras
Home-page: https://gitlab.com/pijarowski.matthias/pytorch_trainer
Author: Matthias Pijarowski
Author-email: pijarowski.matthias@gmail.com
License: MIT
Download-URL: https://gitlab.com/pijarowski.matthias/pytorch_trainer/-/archive/v0.1/pytorch_trainer-v0.1.3.tar.gz
Platform: UNKNOWN
Classifier: Development Status :: 3 - Alpha
Classifier: Intended Audience :: Developers
Classifier: Topic :: Scientific/Engineering :: Artificial Intelligence
Classifier: License :: OSI Approved :: MIT License
Classifier: Programming Language :: Python :: 3
Classifier: Programming Language :: Python :: 3.10
License-File: LICENSE
